Metadata-Version: 1.0
Name: fuzzdict
Version: 0.0.1
Summary: A Python dictionary with fuzzy-matched keys.
Home-page: UNKNOWN
Author: Davide Di Grande
Author-email: davidedigrande94@gmail.com
License: UNKNOWN
Keywords: python
Platform: UNKNOWN
